pyinovonics/__init__.py
pyinovonics/consolelogger.py
pyinovonics/decorators.py
pyinovonics/utils.py
pyinovonics/comms/__init__.py
pyinovonics/comms/base.py
pyinovonics/comms/serial.py
pyinovonics/comms/socket.py
pyinovonics/comms/utils.py
pyinovonics/protocol/__init__.py
pyinovonics/protocol/constants.py
pyinovonics/protocol/packet.py
pyinovonics-0.0.1.dist-info/LICENSE
pyinovonics-0.0.1.dist-info/METADATA
pyinovonics-0.0.1.dist-info/WHEEL
pyinovonics-0.0.1.dist-info/top_level.txt
pyinovonics-0.0.1.dist-info/RECORD
